CHANGES.md
LICENSE.md
MANIFEST.in
README.md
setup.py
eval_scrubber/__init__.py
eval_scrubber/__main__.py
eval_scrubber.egg-info/PKG-INFO
eval_scrubber.egg-info/SOURCES.txt
eval_scrubber.egg-info/dependency_links.txt
eval_scrubber.egg-info/top_level.txt