Metadata-Version: 1.1
Name: eval-scrubber
Version: 0.0.3
Summary: Finds and removes malicious eval base64 PHP code.
Home-page: https://github.com/michigan-com/eval_scrubber
Author: Eric Bower
Author-email: neurosnap@gmail.com
License: The MIT License (MIT)
